mcfinder/__init__.py
mcfinder/background.jpg
mcfinder/config.ico
mcfinder/icon.ico
mcfinder/pinger.py
mcfinder-1.0.0.dist-info/LICENSE.txt
mcfinder-1.0.0.dist-info/METADATA
mcfinder-1.0.0.dist-info/WHEEL
mcfinder-1.0.0.dist-info/entry_points.txt
mcfinder-1.0.0.dist-info/top_level.txt
mcfinder-1.0.0.dist-info/RECORD
